dagster_utils/__init__.py
dagster_utils/config/README.md
dagster_utils/config/__init__.py
dagster_utils/config/configurators.py
dagster_utils/config/preconfiguration_loader.py
dagster_utils/contrib/README.md
dagster_utils/contrib/__init__.py
dagster_utils/contrib/argo_workflows.py
dagster_utils/contrib/data_repo/__init__.py
dagster_utils/contrib/data_repo/jobs.py
dagster_utils/contrib/data_repo/load_tdr_table.py
dagster_utils/contrib/data_repo/snapshot.py
dagster_utils/contrib/data_repo/typing.py
dagster_utils/contrib/google.py
dagster_utils/py.typed
dagster_utils/resources/README.md
dagster_utils/resources/__init__.py
dagster_utils/resources/beam/__init__.py
dagster_utils/resources/beam/beam_runner.py
dagster_utils/resources/beam/dataflow_beam_runner.py
dagster_utils/resources/beam/k8s_beam_runner.py
dagster_utils/resources/beam/local_beam_runner.py
dagster_utils/resources/beam/noop_beam_runner.py
dagster_utils/resources/bigquery.py
dagster_utils/resources/data_repo/__init__.py
dagster_utils/resources/data_repo/api_configuration.py
dagster_utils/resources/data_repo/jade_data_repo.py
dagster_utils/resources/google_storage.py
dagster_utils/resources/sam.py
dagster_utils/resources/slack.py
dagster_utils/testing/README.md
dagster_utils/testing/__init__.py
dagster_utils/testing/filesystem.py
dagster_utils/testing/matchers.py
dagster_utils/testing/resources.py
dagster_utils/tests/__init__.py
dagster_utils/tests/config/__init__.py
dagster_utils/tests/config/test_configurator_aimed_at.py
dagster_utils/tests/config/test_preconfiguration_loader.py
dagster_utils/tests/contrib/__init__.py
dagster_utils/tests/contrib/data_repo/__init__.py
dagster_utils/tests/contrib/data_repo/test_poll_job.py
dagster_utils/tests/contrib/test_argo_workflows.py
dagster_utils/tests/contrib/test_google.py
dagster_utils/tests/resources/__init__.py
dagster_utils/tests/resources/data_repo/__init__.py
dagster_utils/tests/resources/data_repo/test_api_configuration.py
broad_dagster_utils-0.6.7.dist-info/LICENSE
broad_dagster_utils-0.6.7.dist-info/WHEEL
broad_dagster_utils-0.6.7.dist-info/METADATA
broad_dagster_utils-0.6.7.dist-info/RECORD
