Metadata-Version: 2.1
Name: broad-dagster-utils
Version: 0.6.7
Summary: Common utilities and objects for building Dagster pipelines
Home-page: https://github.com/broadinstitute/dagster-utils
License: BSD-3-Clause
Author: Monster Dev
Author-email: monsterdev@broadinstitute.org
Requires-Python: >=3.9,<3.10
Classifier: License :: OSI Approved :: BSD License
Classifier: Programming Language :: Python :: 3
Classifier: Programming Language :: Python :: 3.9
Requires-Dist: PyYAML (>=5.4.1,<6.0.0)
Requires-Dist: argo-workflows (>=5.0.0,<6.0.0)
Requires-Dist: dagster (>=0.12.3,<0.13.0)
Requires-Dist: data-repo-client (>=1.134.0,<2.0.0)
Requires-Dist: google-cloud-bigquery (>=2.15.0,<3.0.0)
Requires-Dist: google-cloud-storage (>=1.38.0,<2.0.0)
Requires-Dist: slackclient (>=2.9.3,<3.0.0)
Project-URL: Repository, https://github.com/broadinstitute/dagster-utils
Project-URL: Release Info, https://github.com/broadinstitute/dagster-utils/releases
